jitxlib/parts/__init__.py
jitxlib/parts/__main__.py
jitxlib/parts/_convert_utils.py
jitxlib/parts/_sanitize.py
jitxlib/parts/_save.py
jitxlib/parts/commands.py
jitxlib/parts/convert.py
jitxlib/parts/query_api.py
jitxlib/parts/_types/__init__.py
jitxlib/parts/_types/capacitor.py
jitxlib/parts/_types/common.py
jitxlib/parts/_types/component.py
jitxlib/parts/_types/inductor.py
jitxlib/parts/_types/landpattern.py
jitxlib/parts/_types/main.py
jitxlib/parts/_types/resistor.py
jitxlib_parts-1.0.0.dist-info/METADATA
jitxlib_parts-1.0.0.dist-info/WHEEL
jitxlib_parts-1.0.0.dist-info/RECORD
