Metadata-Version: 2.4
Name: jitxlib-parts
Version: 1.0.0
Summary: Python interface to JITX parts database
Project-URL: Homepage, https://jitx.com
Project-URL: Documentation, https://docs.jitx.com
Author: JITX
Maintainer: JITX
Classifier: Operating System :: OS Independent
Classifier: Programming Language :: Python :: 3
Requires-Python: >=3.12
Requires-Dist: black==25.1.0
Requires-Dist: dataclasses-json==0.6.7
Requires-Dist: jitx<4.1,>=4.0.0
Requires-Dist: jitxlib-standard<4.1,>=4.0.0
Requires-Dist: websockets>=11.0.0
